qda_toolkit-0.1.7.dist-info/licenses/LICENSE
qdatoolkit/__init__.py
qdatoolkit/controlcharts.py
qdatoolkit/models.py
qda_toolkit-0.1.7.dist-info/METADATA
qda_toolkit-0.1.7.dist-info/WHEEL
qda_toolkit-0.1.7.dist-info/top_level.txt
qda_toolkit-0.1.7.dist-info/RECORD
