Metadata-Version: 2.4
Name: qda-toolkit
Version: 0.1.7
Summary: Quality data analysis toolkit
Home-page: https://github.com/polimi-iclabs/qda
Author: IC Labs (Matteo Bugatti)
Author-email: <matteo.bugatti@polimi.it>
License: CC BY-NC-SA 4.0
Classifier: Programming Language :: Python :: 3
Classifier: Operating System :: OS Independent
Requires-Python: >=3.6
License-File: LICENSE
Requires-Dist: Jinja2==3.1.2
Requires-Dist: matplotlib==3.5.2
Requires-Dist: numpy==1.21.5
Requires-Dist: pandas==1.3.5
Requires-Dist: scipy==1.7.3
Requires-Dist: statsmodels==0.13.5
Dynamic: author
Dynamic: author-email
Dynamic: classifier
Dynamic: description
Dynamic: description-content-type
Dynamic: home-page
Dynamic: license
Dynamic: license-file
Dynamic: requires-dist
Dynamic: requires-python
Dynamic: summary
